{
  "description": "AI Tools Manager - Account management tool for AI Tools",
  "url": "https://github.com/cubezhao/ai-tools-mng/releases/download/v1.9.16/ATM.exe",
  "shortcuts": [
    [
      "ATM.exe",
      "ATM"
    ]
  ],
  "homepage": "https://github.com/cubezhao/ai-tools-mng",
  "autoupdate": {
    "url": "https://github.com/cubezhao/ai-tools-mng/releases/download/v$version/ATM.exe"
  },
  "checkver": "github",
  "bin": "ATM.exe",
  "version": "1.9.16",
  "hash": "c4dc8f49430a27e4a3c9e0212d677d4c46a78ca253a67d0dbac5acacaf2820a6",
  "license": "MIT"
}
